Metadata-Version: 2.1
Name: zettlekasten
Version: 0.0.2
Summary: Zettlekasten at its finest!
Home-page: https://github.com/amirouche/zettlekasten
Author: Amirouche BOUBEKKI
Author-email: amirouche@hyper.dev
License: MIT
Platform: UNKNOWN
Classifier: Programming Language :: Python :: 3
